gcapi/__init__.py
gcapi/apibase.py
gcapi/check_version.py
gcapi/client.py
gcapi/create_strategies.py
gcapi/exceptions.py
gcapi/models.py
gcapi/retries.py
gcapi/transports.py
gcapi/typing.py
gcapi-0.15.1.dist-info/licenses/LICENSE
gcapi-0.15.1.dist-info/METADATA
gcapi-0.15.1.dist-info/WHEEL
gcapi-0.15.1.dist-info/top_level.txt
gcapi-0.15.1.dist-info/RECORD
