Metadata-Version: 2.4
Name: gcapi
Version: 0.15.1
Summary: Python client for the grand-challenge.org REST API
Author: James Meakin
License: Apache-2.0
Project-URL: GitHub, https://github.com/DIAGNijmegen/rse-gcapi
Project-URL: repository, https://github.com/DIAGNijmegen/rse-gcapi.git
Project-URL: documentation, https://diagnijmegen.github.io/rse-gcapi/
Project-URL: issues, https://github.com/DIAGNijmegen/rse-gcapi/issues
Classifier: Development Status :: 3 - Alpha
Classifier: Intended Audience :: Developers
Requires-Python: <4.0,>=3.10
License-File: LICENSE
Requires-Dist: httpx~=0.23.0
Requires-Dist: pydantic
Requires-Dist: packaging
Requires-Dist: grand-challenge-dicom-de-identifier
Dynamic: license-file
